compas_pgs/__init__.py
compas_pgs/__main__.py
compas_pgs/activate.py
compas_pgs/install.py
compas_pgs/rhino/__init__.py
compas_pgs/rhino/helpers.py
compas_pgs/rhino/artists/__init__.py
compas_pgs/rhino/artists/forcevolmeshartist.py
compas_pgs/rhino/artists/formnetworkartist.py
compas_pgs/rhino/artists/networkartist.py
compas_pgs/rhino/artists/volmeshartist.py
compas_pgs/rhino/control/__init__.py
compas_pgs/rhino/control/dynamic_pickers.py
compas_pgs/rhino/control/helpers.py
compas_pgs/rhino/control/inspectors.py
compas_pgs/rhino/control/selectors.py
compas_pgs/rhino/display/__init__.py
compas_pgs/rhino/display/conduits.py
compas_pgs/rhino/display/drawing.py
compas_pgs/rhino/forms/__init__.py
compas_pgs/rhino/forms/attributes.py
compas_pgs/rhino/forms/browser.py
compas_pgs/rhino/forms/modifyattributes.py
compas_pgs/rhino/forms/settings.py
compas_pgs/rhino/forms/src/3gs.png
compas_pgs/rhino/forms/src/brg.png
compas_pgs/rhino/forms/src/eth.png
compas_pgs/rhino/forms/src/index.html
compas_pgs/rhino/forms/src/jquery-3.4.1.slim.min.js
compas_pgs/rhino/forms/src/styles.css
compas_pgs/rhino/objects/__init__.py
compas_pgs/rhino/objects/forcevolmeshobject.py
compas_pgs/rhino/objects/formnetworkobject.py
compas_pgs/rhino/objects/networkobject.py
compas_pgs/rhino/objects/volmeshobject.py
compas_pgs/rhino/wrappers/__init__.py
compas_pgs/rhino/wrappers/modify_diagrams.py
compas_pgs/rhino/wrappers/transform_cell.py
compas_pgs/rhino/wrappers/transform_volmesh.py
compas_pgs/scene/__init__.py
compas_pgs/scene/scene.py
compas_pgs/ui/Rhino/3GS/dev/3GS.rui
compas_pgs/ui/Rhino/3GS/dev/PGS__init_cmd.py
compas_pgs/ui/Rhino/3GS/dev/PGS__scene_clear_cmd.py
compas_pgs/ui/Rhino/3GS/dev/PGS__scene_redraw_cmd.py
compas_pgs/ui/Rhino/3GS/dev/PGS__session_load_cmd.py
compas_pgs/ui/Rhino/3GS/dev/PGS__session_save_cmd.py
compas_pgs/ui/Rhino/3GS/dev/PGS_force_arearize_cmd.py
compas_pgs/ui/Rhino/3GS/dev/PGS_force_from_polysurfaces_cmd.py
compas_pgs/ui/Rhino/3GS/dev/PGS_force_move_vertices_cmd.py
compas_pgs-0.2.0.dist-info/AUTHORS.md
compas_pgs-0.2.0.dist-info/LICENSE
compas_pgs-0.2.0.dist-info/METADATA
compas_pgs-0.2.0.dist-info/WHEEL
compas_pgs-0.2.0.dist-info/entry_points.txt
compas_pgs-0.2.0.dist-info/top_level.txt
compas_pgs-0.2.0.dist-info/RECORD
