Metadata-Version: 2.1
Name: compas-pgs
Version: 0.2.0
Summary: Polyhedral 3D graphic statics based on compas_3gs
Home-page: https://github.com/Block Research Group/compas_pgs
Author: Juney Lee
Author-email: juney.lee@arch.ethz.ch
License: MIT license
Platform: UNKNOWN
Classifier: Development Status :: 4 - Beta
Classifier: Intended Audience :: Developers
Classifier: Topic :: Scientific/Engineering
Classifier: License :: OSI Approved :: MIT License
Classifier: Operating System :: Unix
Classifier: Operating System :: POSIX
Classifier: Operating System :: Microsoft :: Windows
Classifier: Programming Language :: Python
Classifier: Programming Language :: Python :: 3
Classifier: Programming Language :: Python :: 3.6
Classifier: Programming Language :: Python :: 3.7
Classifier: Programming Language :: Python :: 3.8
Classifier: Programming Language :: Python :: Implementation :: CPython
Requires-Python: >=3.6
License-File: LICENSE
License-File: AUTHORS.md
Requires-Dist: compas (>=1.10.0)
Requires-Dist: compas-3gs
